devtools_markdown/__init__.py
devtools_markdown-1.0.1.dist-info/METADATA
devtools_markdown-1.0.1.dist-info/WHEEL
devtools_markdown-1.0.1.dist-info/top_level.txt
devtools_markdown-1.0.1.dist-info/RECORD
