Metadata-Version: 2.1
Name: devtools-markdown
Version: 1.0.1
Summary: Markdown preview
Home-page: https://devtools.at/tools/markdown-preview
Author: DevTools.at
Author-email: hello@devtools.at
Project-URL: Homepage, https://devtools.at/tools/markdown-preview
Project-URL: Repository, https://github.com/devtools-at/markdown-preview
Classifier: Development Status :: 4 - Beta
Classifier: Intended Audience :: Developers
Classifier: License :: OSI Approved :: MIT License
Classifier: Programming Language :: Python :: 3
Requires-Python: >=3.8
